demotype/__init__.py
demotype/__main__.py
demotype/demo.py
demotype-0.0.1.dist-info/AUTHORS
demotype-0.0.1.dist-info/LICENSE
demotype-0.0.1.dist-info/METADATA
demotype-0.0.1.dist-info/WHEEL
demotype-0.0.1.dist-info/entry_points.txt
demotype-0.0.1.dist-info/top_level.txt
demotype-0.0.1.dist-info/RECORD
