Metadata-Version: 2.1
Name: demotype
Version: 0.0.1
Summary: A command-line utility that simulates typing text from an input file.
Home-page: https://gitlab.com/nul.one/demotype
Author: Predrag Mandic
Author-email: predrag@nul.one
License: BSD
Download-URL: https://gitlab.com/nul.one/demotype/-/archive/0.0.1/demotype-0.0.1.tar.gz
Platform: UNKNOWN
Classifier: Development Status :: 4 - Beta
Classifier: Environment :: Console
Classifier: License :: OSI Approved :: BSD License
Classifier: Natural Language :: English
Classifier: Operating System :: POSIX :: Linux
Classifier: Programming Language :: Python :: 3 :: Only
Classifier: Topic :: Utilities
Requires-Python: >=3.4.6
Requires-Dist: click (<8.0,>=6.7)
Requires-Dist: pynput (<2.0,>=1.4.2)
